vk_requests/__init__.py
vk_requests/api.py
vk_requests/exceptions.py
vk_requests/session.py
vk_requests/settings.py
vk_requests/streaming.py
vk_requests/utils.py
vk_requests-1.1.2.dist-info/DESCRIPTION.rst
vk_requests-1.1.2.dist-info/METADATA
vk_requests-1.1.2.dist-info/RECORD
vk_requests-1.1.2.dist-info/WHEEL
vk_requests-1.1.2.dist-info/metadata.json
vk_requests-1.1.2.dist-info/top_level.txt
