Metadata-Version: 2.0
Name: vk-requests
Version: 1.1.2
Summary: vk.com requests for humans. API library for vk.com
Home-page: https://github.com/prawn-cake/vk-requests
Author: Maksim Ekimovskii
Author-email: ekimovsky.maksim@gmail.com
License: MIT
Platform: UNKNOWN
Classifier: Intended Audience :: Developers
Classifier: Programming Language :: Python :: 2.7
Classifier: Programming Language :: Python :: 3.4
Classifier: Programming Language :: Python :: 3.5
Classifier: Programming Language :: Python :: 3.6
Requires-Dist: six
Requires-Dist: requests (>=2.8.1)
Requires-Dist: beautifulsoup4 (>=4.4.1)
Provides-Extra: streaming
Requires-Dist: websockets; python_version>="3.4" and extra == 'streaming'
